hamiltonian_ai/__init__.py
hamiltonian_ai/data_processing.py
hamiltonian_ai/loss_functions.py
hamiltonian_ai/models.py
hamiltonian_ai/optimizers.py
hamiltonian_ai/utils.py
hamiltonian_ai-0.3.0.dist-info/LICENSE.txt
hamiltonian_ai-0.3.0.dist-info/METADATA
hamiltonian_ai-0.3.0.dist-info/WHEEL
hamiltonian_ai-0.3.0.dist-info/top_level.txt
hamiltonian_ai-0.3.0.dist-info/RECORD
