Metadata-Version: 2.1
Name: hamiltonian_ai
Version: 0.3.0
Summary: A Hamiltonian-inspired approach for AI optimization
Author-email: Javier Marin <javierl@jmarin.info>
Requires-Python: >=3.7
License-File: LICENSE.txt
Requires-Dist: torch >=1.7.0
Requires-Dist: numpy >=1.19.0
Requires-Dist: scikit-learn >=0.24.0
Requires-Dist: imbalanced-learn >=0.8.0
